README.rst
setup.py
look/__init__.py
look/captcha.py
look/cnn_model.py
look/cut.py
look/dataset.py
look/look_example.zip
look/model.pkl
look/one_hot.py
look/setting.py
look.egg-info/PKG-INFO
look.egg-info/SOURCES.txt
look.egg-info/dependency_links.txt
look.egg-info/entry_points.txt
look.egg-info/requires.txt
look.egg-info/top_level.txt