Metadata-Version: 1.1
Name: look
Version: 0.2.2
Summary: Look
Home-page: https://github.com/tonglei100/look
Author: Leo Tong
Author-email: tonglei@qq.com
License: Apache License, Version 2.0
Platform: UNKNOWN
Classifier: Environment :: Web Environment
Classifier: Intended Audience :: Developers
Classifier: Operating System :: OS Independent
Classifier: Topic :: Software Development :: Libraries :: Python Modules
Classifier: Programming Language :: Python :: 3
